Metadata-Version: 2.1
Name: wos-tabfile
Version: 0.0.1a1
Summary: Extract information from the exported Web of Science's tab delimited text file
Home-page: UNKNOWN
Author: Donghua Chen
Author-email: douglaschan@126.com
License: UNKNOWN
Keywords: Web of Science,bibliometric analysis,WoS keyword analysis,WoS file
Platform: UNKNOWN
Classifier: Development Status :: 3 - Alpha
Classifier: Intended Audience :: Developers
Classifier: Topic :: Software Development :: Build Tools
Classifier: License :: OSI Approved :: MIT License
Classifier: Programming Language :: Python :: 3
Classifier: Programming Language :: Python :: 3.6
Classifier: Programming Language :: Python :: 3.7
Classifier: Programming Language :: Python :: 3.8
Classifier: Programming Language :: Python :: 3.9
Classifier: Programming Language :: Python :: 3 :: Only
Requires-Python: >=3.6, <4
Provides-Extra: dev
Provides-Extra: test
License-File: LICENSE.txt
